fds/__init__.py
fds/sdk/__init__.py
fds/sdk/FactSetIntradayTickHistory/__init__.py
fds/sdk/FactSetIntradayTickHistory/api_client.py
fds/sdk/FactSetIntradayTickHistory/configuration.py
fds/sdk/FactSetIntradayTickHistory/exceptions.py
fds/sdk/FactSetIntradayTickHistory/model_utils.py
fds/sdk/FactSetIntradayTickHistory/rest.py
fds/sdk/FactSetIntradayTickHistory/api/__init__.py
fds/sdk/FactSetIntradayTickHistory/api/first_trade_api.py
fds/sdk/FactSetIntradayTickHistory/api/last_trade_api.py
fds/sdk/FactSetIntradayTickHistory/api/quote_at_time_api.py
fds/sdk/FactSetIntradayTickHistory/api/tick_history_api.py
fds/sdk/FactSetIntradayTickHistory/api/trades_at_time_api.py
fds/sdk/FactSetIntradayTickHistory/apis/__init__.py
fds/sdk/FactSetIntradayTickHistory/model/__init__.py
fds/sdk/FactSetIntradayTickHistory/model/fields.py
fds/sdk/FactSetIntradayTickHistory/model/intervals.py
fds/sdk/FactSetIntradayTickHistory/model/specialfield.py
fds/sdk/FactSetIntradayTickHistory/model/tickhistory_response.py
fds/sdk/FactSetIntradayTickHistory/models/__init__.py
fds.sdk.FactSetIntradayTickHistory-0.21.14.dist-info/LICENSE
fds.sdk.FactSetIntradayTickHistory-0.21.14.dist-info/METADATA
fds.sdk.FactSetIntradayTickHistory-0.21.14.dist-info/WHEEL
fds.sdk.FactSetIntradayTickHistory-0.21.14.dist-info/top_level.txt
fds.sdk.FactSetIntradayTickHistory-0.21.14.dist-info/RECORD
